{
  "creds": {
    "noiseKey": {
      "private": {
        "type": "Buffer",
        "data": "kIr9co33bRY2VJRBpUHV1qdWlZWCqtT3b45NrGOf4lM="
      },
      "public": {
        "type": "Buffer",
        "data": "jtjmNUVpijyjB3mHc0tl8rPsZV1GFRENo0jSponJsHY="
      }
    },
    "signedIdentityKey": {
      "private": {
        "type": "Buffer",
        "data": "yMZrn4g0q6jN45Fji3v78GlCdhZM15A+XPZ1O8esCmg="
      },
      "public": {
        "type": "Buffer",
        "data": "SMK5Mkc+QgXLSBQVWB0M5gbVW89G8LzIgH4V0QzYXHM="
      }
    },
    "signedPreKey": {
      "keyPair": {
        "private": {
          "type": "Buffer",
          "data": "YMd+7rTj8bS5jp5gy7FdaP2HUd1K2zNqzGAHovZyfnA="
        },
        "public": {
          "type": "Buffer",
          "data": "NQTnWy2kpfmEnsUn838hK3dg1plmjBkQDDZgv/HY8V0="
        }
      },
      "signature": {
        "type": "Buffer",
        "data": "uRiTNDW8hn0L/Iaekqq1ge3t9ApiK5sINRjyn3julYWf9ynf+IPiCUDd7oas3AGVGi4O76P7hQJe8B/xnVyQCA=="
      },
      "keyId": 1
    },
    "registrationId": 50,
    "advSecretKey": "tdTB5gKh//oATUieOvO1+ZN7b6Z9tW4ohzzoTZp+XgY=",
    "processedHistoryMessages": [
      {
        "key": {
          "remoteJid": "6283803556993@s.whatsapp.net",
          "fromMe": true,
          "id": "DA0B0BC21583C65FD98430EF947AB7D0"
        },
        "messageTimestamp": 1667546872
      },
      {
        "key": {
          "remoteJid": "6283803556993@s.whatsapp.net",
          "fromMe": true,
          "id": "6C124FAF3C380CD5A174AB20BA1E0F37"
        },
        "messageTimestamp": 1667546872
      },
      {
        "key": {
          "remoteJid": "6283803556993@s.whatsapp.net",
          "fromMe": true,
          "id": "D2513A0C46AF2527D7CFACB6E2C49F06"
        },
        "messageTimestamp": 1667546897
      }
    ],
    "nextPreKeyId": 31,
    "firstUnuploadedPreKeyId": 31,
    "accountSettings": {
      "unarchiveChats": false
    },
    "account": {
      "details": "CJuZzNMHEO39kpsGGAE=",
      "accountSignatureKey": "EkwXqhWAVlKowphstNDPBnjlNsPCDhcEJZ0+Z0KpMU4=",
      "accountSignature": "6IR7uDYwfmfRKBmC97+Ne11VdVpcWCrTc7lUX3Dyu4QHUyuO4hbIaVsbWbH9+Uug5DJt3OpjGUD9qcVy25RyCA==",
      "deviceSignature": "JxaIhKL02y0HaebMC2GjNTOkhMO/ZqvKeMNBl1+A1hm/hTtkr8YkLoyuFIzUX30IlpndqVFgyvsnZUcb2QsZBA=="
    },
    "me": {
      "id": "6283803556993:48@s.whatsapp.net",
      "name": "Galactic"
    },
    "signalIdentities": [
      {
        "identifier": {
          "name": "6283803556993:48@s.whatsapp.net",
          "deviceId": 0
        },
        "identifierKey": {
          "type": "Buffer",
          "data": "BRJMF6oVgFZSqMKYbLTQzwZ45TbDwg4XBCWdPmdCqTFO"
        }
      }
    ],
    "platform": "android",
    "lastAccountSyncTimestamp": 1667546865,
    "myAppStateKeyId": "AAAAAAQv"
  },
  "keys": {
    "preKeys": {
      "1": {
        "private": {
          "type": "Buffer",
          "data": "OEU+i1J3DemIaLbVdd6aX6lG3fitvsalc4BF2EWYZ1M="
        },
        "public": {
          "type": "Buffer",
          "data": "ghNsqisrcYZGOf+syLlrdu87oS6sR6ctzshtafOH6G8="
        }
      },
      "2": {
        "private": {
          "type": "Buffer",
          "data": "sCzskATU98Dl/2u1S4qjvS2V58PpA9A43HVJjwbUtWc="
        },
        "public": {
          "type": "Buffer",
          "data": "4bPnIJZdIY0tvsSku6pDwk70tOvF7JbiKZwv1Cop4yc="
        }
      },
      "3": {
        "private": {
          "type": "Buffer",
          "data": "sL271tMwNsfKBcJAXbl45f1j00DV4OrAlB6tf7EqqUY="
        },
        "public": {
          "type": "Buffer",
          "data": "RKyHm418w2xiDFD5jiXzUTeAF/4einHqKJ9nR4Cw7Qw="
        }
      },
      "4": {
        "private": {
          "type": "Buffer",
          "data": "KPXQl8t46XpSqQbMCxmk9p270rfMNOTmj2gkeAkl4V8="
        },
        "public": {
          "type": "Buffer",
          "data": "VP/7qRp3baDcIG6dr+Uzita56NFR9WryFeA0jno0UCE="
        }
      },
      "5": {
        "private": {
          "type": "Buffer",
          "data": "MAeFT+pgXx2gvbIkGzpSW2oT3wtYCbGWp5wF2ix4XlI="
        },
        "public": {
          "type": "Buffer",
          "data": "XdnAJP9c9CgikZxaBJdEOgiK1tCd3RbxL58j43qk1hI="
        }
      },
      "6": null,
      "7": {
        "private": {
          "type": "Buffer",
          "data": "kKsPIKX1XAzkCoB6bB5MQF3zrQ3nHY5vZs5upYccTG8="
        },
        "public": {
          "type": "Buffer",
          "data": "hubHwTD/8Olo1S9LFl6ZaBt/5yD3zb8Euwl3Zput/jE="
        }
      },
      "8": {
        "private": {
          "type": "Buffer",
          "data": "ECidf8IkR3u28vEzyR38fvwRe1z/oKOcdIzh5aEjhGo="
        },
        "public": {
          "type": "Buffer",
          "data": "KmA5pCktLNRYFQJwzRWd/a9GuqJet+8DGCOFjDnqDQ8="
        }
      },
      "9": {
        "private": {
          "type": "Buffer",
          "data": "GF5OC2iHIf/OGnqqJ0BLd4cjVZgH9geXbjrKT5OHIFM="
        },
        "public": {
          "type": "Buffer",
          "data": "3Be0oKjKv7PoHKvz56CFUJP1/FZnxPBVm/OQGAVijxc="
        }
      },
      "10": {
        "private": {
          "type": "Buffer",
          "data": "8AeGuCGgpRu8coHxAXUdVBID8+QweI7Ez40g6zvfDkM="
        },
        "public": {
          "type": "Buffer",
          "data": "x13x172IE8lvoErXiF/sjLLWysv6tMeD+ZN5XBjVohY="
        }
      },
      "11": {
        "private": {
          "type": "Buffer",
          "data": "EL+txPLmbWcuLdEMgjZVtL9UB67d9AGLh/EmNtu7iEs="
        },
        "public": {
          "type": "Buffer",
          "data": "WP0VBivOob8Zv3Fjs0nR1bBjwkWNdalhmkW6bpHTQiA="
        }
      },
      "12": {
        "private": {
          "type": "Buffer",
          "data": "WEkvON6jEZh9pFne97e1zvRd5g7r++L4k6IEcA3yY0c="
        },
        "public": {
          "type": "Buffer",
          "data": "pyzZWLr3K7PfxLTJVG2nnmGaZ9qpyHqLmNcFivYx+A0="
        }
      },
      "13": {
        "private": {
          "type": "Buffer",
          "data": "GPzwaWk87yyD2qd3GwrQZC3KDpX7ixnc8pOi9qQI6Xs="
        },
        "public": {
          "type": "Buffer",
          "data": "qTRuY+KxntoW7gNz+ecdlrmMJuJLUI0L1Z8vIL8layw="
        }
      },
      "14": null,
      "15": null,
      "16": {
        "private": {
          "type": "Buffer",
          "data": "YBYIMwozPghyFqpq3GOIAP51nG5Co77IZ2MJzemNClY="
        },
        "public": {
          "type": "Buffer",
          "data": "z+6Cz2prPqzlQMgPs6ktqjsj7+E+5DQTQed7YPsq8x8="
        }
      },
      "17": {
        "private": {
          "type": "Buffer",
          "data": "oFs5qTsiE/wa/lG6vqWH0j1rjBll5oJZ9SK2a4tNk08="
        },
        "public": {
          "type": "Buffer",
          "data": "NJaQCyKN8HXaYjcXzRwP7VpnyErPRDhf1WGnwrz+FjI="
        }
      },
      "18": {
        "private": {
          "type": "Buffer",
          "data": "MPExa+IDvdZAR0XYIQWN4GJeITAz9diWcelIGwg5h08="
        },
        "public": {
          "type": "Buffer",
          "data": "s3G720F4EjKt1mp43DXUwhDgogRoVMDjXBR3fXH+kkQ="
        }
      },
      "19": {
        "private": {
          "type": "Buffer",
          "data": "KIAxIj/NpkPMqzXs1/jWRCxn9+T9ot04dvj3Uoqyunc="
        },
        "public": {
          "type": "Buffer",
          "data": "hSeC5uKIvKUfl9B0+m5/FR8j22Wq08+hEDyceRHdIUs="
        }
      },
      "20": {
        "private": {
          "type": "Buffer",
          "data": "+Nfuq//V4v3y+MtAH1a8cYkuThpLPZs9Kn5qw6nPHUo="
        },
        "public": {
          "type": "Buffer",
          "data": "LUFx0OE88tYHKiFprxCOKYzcfAblVmDmZrhPzFilSTs="
        }
      },
      "21": {
        "private": {
          "type": "Buffer",
          "data": "iCmMU2rRlMeCzfA0REr0IyFWERTkvOk2UDxJ0TyCHl8="
        },
        "public": {
          "type": "Buffer",
          "data": "MG6BErbBMjjtsYVoZl3TiWpUdNJMaff8GJZq/3z7mWE="
        }
      },
      "22": {
        "private": {
          "type": "Buffer",
          "data": "0JoLhhYKyFZE8Q2o2xVt05Avwr47i9QBCIafizTvWWc="
        },
        "public": {
          "type": "Buffer",
          "data": "iKX6bWpJtLznpeMXFlu7F3ZgHrBukXjkDbcIlmBHJ1s="
        }
      },
      "23": {
        "private": {
          "type": "Buffer",
          "data": "KEwPwIubFfe+2W/jU8I6N8iBLr62fGyY7ERGKyrRkmc="
        },
        "public": {
          "type": "Buffer",
          "data": "ivaRFSkPkF/G8JKl06CjerzXNGTlPp6+X0ne/gBPTh0="
        }
      },
      "24": {
        "private": {
          "type": "Buffer",
          "data": "SN8m3X/4E8c9yhaHGFQitbS2hSYqGT8gQ7lwn4acN10="
        },
        "public": {
          "type": "Buffer",
          "data": "47cAhzTIuSDjYjrn5GNABr1CqwNjq2qQTOKEBILqPVI="
        }
      },
      "25": {
        "private": {
          "type": "Buffer",
          "data": "wKW+4Ns+rVLcojzuZ0mwnfq28J7sTxEHeMqWbJWlPWc="
        },
        "public": {
          "type": "Buffer",
          "data": "YcR/aigqbutiwHvdIKbQFMEKwiyBax13FIgk9dd7REw="
        }
      },
      "26": {
        "private": {
          "type": "Buffer",
          "data": "kCCDTjHa8wG4hb8qs4ao4ljVKA3A4EsePFpPzGZS9k0="
        },
        "public": {
          "type": "Buffer",
          "data": "xGcwM8o6UGhWYePrxurdbG3et+0IjuUM+MnuPq5q83E="
        }
      },
      "27": {
        "private": {
          "type": "Buffer",
          "data": "gAI8FH+BMpX4ypKxjO7dNsuBY8KufUXwXVyQviPgU10="
        },
        "public": {
          "type": "Buffer",
          "data": "aRg4ULDY4TZrGcSxefuvrHu7e+MXSjENgmpyTA69OHg="
        }
      },
      "28": {
        "private": {
          "type": "Buffer",
          "data": "4L2vabAkOlyyKEQMNSkk3EX4RvxHp/76FNS3hxvKI2U="
        },
        "public": {
          "type": "Buffer",
          "data": "7Urc2kkKBhL3InrPeFJqq6xk6sYKLkzliE2NRTYQREE="
        }
      },
      "29": {
        "private": {
          "type": "Buffer",
          "data": "AAkjaKF/i2IX63jTN0YV+rySe+kw9VwYa9ov2dpY/Xk="
        },
        "public": {
          "type": "Buffer",
          "data": "+kpuFNWgTgniZCk15E7L//ppuQOoK4wBf2Lpa/Yn2Bk="
        }
      },
      "30": {
        "private": {
          "type": "Buffer",
          "data": "8IvSdOiWyHwIqXET7oEOP7K+ZQNDFL5+8JdFeVaiimc="
        },
        "public": {
          "type": "Buffer",
          "data": "9eb0xZnMl1yWwLsciT5ZvqI6JMFh+qKHbKWUds0CMEc="
        }
      }
    },
    "sessions": {
      "6283803556993.0": {
        "_sessions": {
          "BRGc+Oq7pKA0see276gqq2ZeIMnGZaWjezrHO2BYqqpP": {
            "registrationId": 49023696,
            "currentRatchet": {
              "ephemeralKeyPair": {
                "pubKey": "BfivRuF18oxeQqa5hEuywHhr3XZfLN92re3c/SRx0Z5P",
                "privKey": "oOhj6vy8/OX9Znfja9ILo2E1lsHU3BIvO9/NupP87UA="
              },
              "lastRemoteEphemeralKey": "BQri9mja/RYSK/GpSsx5Fz6g82wpEsx4yCboaQSmEYs3",
              "previousCounter": 1,
              "rootKey": "u8clrh8wmfTngRQ9LItckQhx+TBaUsY09Ox5xBDBKks="
            },
            "indexInfo": {
              "baseKey": "BRGc+Oq7pKA0see276gqq2ZeIMnGZaWjezrHO2BYqqpP",
              "baseKeyType": 2,
              "closed": -1,
              "used": 1667546896331,
              "created": 1667546865716,
              "remoteIdentityKey": "BRJMF6oVgFZSqMKYbLTQzwZ45TbDwg4XBCWdPmdCqTFO"
            },
            "_chains": {
              "BYz7pGhs8TRfD0WdvEsAQzn/r0aeu7urLv336LZpFAAp": {
                "chainKey": {
                  "counter": 6
                },
                "chainType": 2,
                "messageKeys": {}
              },
              "BQri9mja/RYSK/GpSsx5Fz6g82wpEsx4yCboaQSmEYs3": {
                "chainKey": {
                  "counter": 0,
                  "key": "L2iSPnKx7VnLYTbwp5eR0C5dmhQk4PMyw7KnCdJvdJY="
                },
                "chainType": 2,
                "messageKeys": {}
              },
              "BfivRuF18oxeQqa5hEuywHhr3XZfLN92re3c/SRx0Z5P": {
                "chainKey": {
                  "counter": -1,
                  "key": "kVvNFgJhfR923GGje4MKpQVWu3LPxAVVms2gyLlX0Pk="
                },
                "chainType": 1,
                "messageKeys": {}
              }
            }
          }
        },
        "version": "v1"
      },
      "6287789779960:20.0": {
        "_sessions": {
          "BU+5JhDoNP0VZ4PVYEyrxAi1WF1NVss053SZkD6CKZ44": {
            "registrationId": 65,
            "currentRatchet": {
              "ephemeralKeyPair": {
                "pubKey": "Bapia8ghWHWEVx/GIX+qj4oHUMPvUuZBTq1Km4PWyZZB",
                "privKey": "QKkDc57hIrl4jL1Xw83S3BViGKHIMKBYrBjX+JIYuXM="
              },
              "lastRemoteEphemeralKey": "BcPXHgx0NHEVOYRml4nHsATXyP+YPtXUKX89iTDnVD0C",
              "previousCounter": 0,
              "rootKey": "pUVARPAV/Hh0WR+a3zschi0WWpi1jMFIiQA7krYe32Y="
            },
            "indexInfo": {
              "baseKey": "BU+5JhDoNP0VZ4PVYEyrxAi1WF1NVss053SZkD6CKZ44",
              "baseKeyType": 2,
              "closed": -1,
              "used": 1667546884141,
              "created": 1667546884141,
              "remoteIdentityKey": "BXEU7muIQrTR00oviyzAJEQXNcaQXYnlGfnaASoi2yYX"
            },
            "_chains": {
              "BcPXHgx0NHEVOYRml4nHsATXyP+YPtXUKX89iTDnVD0C": {
                "chainKey": {
                  "counter": 0,
                  "key": "l+4+TVMm4SOVtssx7yQ64YoC3IHfv4URtsmFyrYH6HA="
                },
                "chainType": 2,
                "messageKeys": {}
              },
              "Bapia8ghWHWEVx/GIX+qj4oHUMPvUuZBTq1Km4PWyZZB": {
                "chainKey": {
                  "counter": -1,
                  "key": "rcI6KH5SYhulrK4SOZgH/uOxg5KM8bT5BnnEZz8gpHA="
                },
                "chainType": 1,
                "messageKeys": {}
              }
            }
          }
        },
        "version": "v1"
      },
      "6285892391718:75.0": {
        "_sessions": {
          "BbGC3yBX8ks4yvu/T1mP0RuFySFhdj+vZgtH8eCXBppn": {
            "registrationId": 111,
            "currentRatchet": {
              "ephemeralKeyPair": {
                "pubKey": "BVqzpoFOUroadWwtDj41B1Yn2aiBgk7B54svkQOHvzwL",
                "privKey": "+KQ+RgNigP8jpY3kfIcmqKSPc/nHOajvAdEqyFWumEw="
              },
              "lastRemoteEphemeralKey": "BWWvXAK7xNC9tpWuOmFRx9EayqBisUgrLPuKVMMG+JQr",
              "previousCounter": 0,
              "rootKey": "mcraeo7bZBmNjQZfWK00aW+P2Eacv0O3MfqalGJjVRg="
            },
            "indexInfo": {
              "baseKey": "BbGC3yBX8ks4yvu/T1mP0RuFySFhdj+vZgtH8eCXBppn",
              "baseKeyType": 2,
              "closed": -1,
              "used": 1667546884180,
              "created": 1667546884180,
              "remoteIdentityKey": "BRxiaaTEf2KbpLr07WiX5iT9X2GTizyCotTHGpiojlct"
            },
            "_chains": {
              "BWWvXAK7xNC9tpWuOmFRx9EayqBisUgrLPuKVMMG+JQr": {
                "chainKey": {
                  "counter": 0,
                  "key": "VRDTR/lRehYOQfqBeBnDYVV4Gz3crGBzdHHQQmpJuhU="
                },
                "chainType": 2,
                "messageKeys": {}
              },
              "BVqzpoFOUroadWwtDj41B1Yn2aiBgk7B54svkQOHvzwL": {
                "chainKey": {
                  "counter": -1,
                  "key": "3S0Jew11qXFgXfX6IQZxRLQnDUR1WX1cinxLnv566XU="
                },
                "chainType": 1,
                "messageKeys": {}
              }
            }
          }
        },
        "version": "v1"
      },
      "6283897009834.0": {
        "_sessions": {
          "BT8IF2bx1TsjwRSVb9U7alZ2497klibWIWvt9n8Modhd": {
            "registrationId": 1121507129,
            "currentRatchet": {
              "ephemeralKeyPair": {
                "pubKey": "BdRhvQFSgVPPuBLK2LQO9czzUE0ihgoZldlFDT/ockka",
                "privKey": "II412uJb4coTXiLXXIEt88aOOXGyJjwII+nP8iNJGns="
              },
              "lastRemoteEphemeralKey": "BcjZX7flyOfjRzK3U5+QTzMMnpugRREr28bIfaFvkJVX",
              "previousCounter": 0,
              "rootKey": "fb2uaGAW+yDCxOOyF0aR6d9BwFQ+eQ4L0ABvrSwy7Xo="
            },
            "indexInfo": {
              "baseKey": "BT8IF2bx1TsjwRSVb9U7alZ2497klibWIWvt9n8Modhd",
              "baseKeyType": 2,
              "closed": -1,
              "used": 1667546884211,
              "created": 1667546884211,
              "remoteIdentityKey": "BU1zB2HxtRnUsnfsn+Xqxk7cORLIwKyRjlVGWOwa6T9T"
            },
            "_chains": {
              "BcjZX7flyOfjRzK3U5+QTzMMnpugRREr28bIfaFvkJVX": {
                "chainKey": {
                  "counter": 0,
                  "key": "QAWy4VbdsMZcbLT+yJaml3p5gZJlWKGSzF1xdsFzg7g="
                },
                "chainType": 2,
                "messageKeys": {}
              },
              "BdRhvQFSgVPPuBLK2LQO9czzUE0ihgoZldlFDT/ockka": {
                "chainKey": {
                  "counter": -1,
                  "key": "b+9eUbDZiOiYVEFnC/x2ukIQoAlAhjBaJKjt/O+qcew="
                },
                "chainType": 1,
                "messageKeys": {}
              }
            }
          }
        },
        "version": "v1"
      }
    },
    "appStateSyncKeys": {
      "AAAAAAQv": {
        "keyData": "iME5pyrGvHj2S7OA45dqtC/ql4o+rgNyg0GKxm8xfL4=",
        "fingerprint": {
          "rawId": 2054360219,
          "currentIndex": 1,
          "deviceIndexes": [
            0,
            1
          ]
        },
        "timestamp": "1667546866537"
      }
    },
    "senderKeys": {
      "120363040666024098@g.us::6287789779960:20::0": [
        {
          "senderKeyId": 21036783,
          "senderChainKey": {
            "iteration": 17,
            "seed": "r/vbbysIXDuZwQa848bjLS5P5VfroxpZYZWfgS2RwT0="
          },
          "senderSigningKey": {
            "public": "BetJN7w/9QKRdcLP1OzVOnqExrlisN8Vi4czYVcSjw8d"
          }
        }
      ],
      "120363040666024098@g.us::6285892391718:75::0": [
        {
          "senderKeyId": 1431735924,
          "senderChainKey": {
            "iteration": 1,
            "seed": "w99xMXPFfsjkYZRHzRwawwr5RoxkarDSk7FKfhuuqrg="
          },
          "senderSigningKey": {
            "public": "Bb3lGX5HbPwypMuMsN/fsO/zYsv58y7J4OCXQWY60utE"
          }
        }
      ],
      "120363040666024098@g.us::6283897009834::0": [
        {
          "senderKeyId": 1966250480,
          "senderChainKey": {
            "iteration": 0,
            "seed": "xXj9yHjunzAYOufXzqkHHLpwE/kljuj5leQYqWSCVDU="
          },
          "senderSigningKey": {
            "public": "BZHEBsvZtb8YqopAHuQO1fTvYSMpNfMSoaQABo7tCGt/"
          }
        }
      ],
      "120363044408246178@g.us::6283803556993::0": [
        {
          "senderKeyId": 437381385,
          "senderChainKey": {
            "iteration": 5,
            "seed": "+I/B8zdUYdzTknoVRNbpm3kDEmDmVXuPRVz4/XBnDwc="
          },
          "senderSigningKey": {
            "public": "BWeXrLDVQ92PN/xMQmvR77O+gQJSLgBTRNgJlhEs40kl"
          }
        }
      ],
      "120363044408246178@g.us::6283803556993:48::0": [
        {
          "senderKeyId": 1259145513,
          "senderChainKey": {
            "iteration": 3,
            "seed": "shRvqlfwtS8/cqyBMO/QoXxHf4W+GS6V2aAAYwmj2T0="
          },
          "senderSigningKey": {
            "public": "BUG7vqMdrcLTgPiIfrn8ruMHrokhXEjzylC/cclPzzos",
            "private": "6NQ9JfuAwGXzu4iAKEtjXXzCdQQIbRtteQu6mEtJFmQ="
          }
        }
      ]
    },
    "appStateVersions": {
      "critical_block": {
        "version": 1,
        "hash": {
          "type": "Buffer",
          "data": "bgrnozDw/UVnfCmn4rLm0JupDPPmE7HSHEWZAv0vXskY9YuNzTzDDtA/7rBnbsk6atj0Zyl22EvcKkkE76BV6MvS19iCt0INpbgDRwoaWp3dfBwf4cuFQp72FEXxA/8C7RwKHeR4lwdkg3jQV7YY5iMYFnEDANWRZkcSt5sfLjE="
        },
        "indexValueMap": {
          "GGx+tp90HnYGqaoqVBrvxbSS0TGNbxdpG1gj3XnpkRU=": {
            "valueMac": {
              "type": "Buffer",
              "data": "3Pzh9+d/rtcjSmoQ7tfhEX6BN3KTS3st7mFq02YmqoM="
            }
          },
          "tbB87mpTnzpoXqSXBTWiHZjAKqCfYKGuXSxrxa9L5WU=": {
            "valueMac": {
              "type": "Buffer",
              "data": "13TpKggjzywJSZQ7Zjbwu9FhmBy9prixYLAqi5VJ91I="
            }
          }
        }
      },
      "regular": {
        "version": 1,
        "hash": {
          "type": "Buffer",
          "data": "ue/TGJr4CbJTv6enGR5yQQTdvzZHJGy+qOYR2MJfdloAc8l8AoOa1Q8vG5PDjZIxzWEFR80NIyZ+v/iP/pqq0x8z7YMP27atEbSTtg+fLqMARxNkPm7wt4OvtgLKjCOdy6ySwwJJoSifrcQsmHaP5RNoKlVwYPt6+d41f5KM7+0="
        },
        "indexValueMap": {
          "K7JIAackkBnpO77KJwk3VsABOkQG4WCTfzIOH6t06LM=": {
            "valueMac": {
              "type": "Buffer",
              "data": "csuYmEP2bf+7Xf+APr/5qFbmO2N/OG15pTbCWrdi0oc="
            }
          }
        }
      },
      "critical_unblock_low": {
        "version": 1,
        "hash": {
          "type": "Buffer",
          "data": "4TQtrU7HV9tPYqHUdPlTqemUobTIxMlSbM/A9Ngw0X48yz53Oi3ePJ6Yc7+Vn4edKSbR1DfgTMqpTU0wLKgel9+kvZUQUZlLXXGnund+ySPk4i5h2sb7KmM8xc8wVrvkGtIDpyHqcp1a4ebMisiS9cNv5Z08lM9ildzMrPX4JGk="
        },
        "indexValueMap": {
          "uphtxwF6biXVjpg3azF0bKnk8FzynBhQ6MEmsVQdMjo=": {
            "valueMac": {
              "type": "Buffer",
              "data": "PInt90K2NOlqvTcBwT1nW7EDxzlVivoBvJ2SRNGleq0="
            }
          },
          "sE9usRFEyOCZLUCHGWVYiHxttqADI3QuxVbrM8FWSXA=": {
            "valueMac": {
              "type": "Buffer",
              "data": "IYqbjAWx4j/xd3klDzraqZ5ccwAo7OJLUsIfrZ5cwXs="
            }
          },
          "arTchtaZcqV6oNMuzCvLf8TZ25+vNbX/MTU0MQFxRZ4=": {
            "valueMac": {
              "type": "Buffer",
              "data": "340kZMj3aX+Cfa7XlsVNR/qE4jRORK9Nbkcit7G2J6c="
            }
          },
          "YSgqh/2Cjo7zM62D2Igot24nvjUsAzVdct/1wc48BDE=": {
            "valueMac": {
              "type": "Buffer",
              "data": "GByAxIeKzJKyRWSS0VIAtw/OZvc8wV+CiYTgF6EENUk="
            }
          },
          "KjSp2OZnqapVR51IukQZ6GOvMKJMXRKaJAdrxHYu00g=": {
            "valueMac": {
              "type": "Buffer",
              "data": "7q846o3uZeKupH1OAW91nA9Jm69ynwHZDoEdJrqYQBc="
            }
          },
          "gF24CopM30+Aem0eyQ0OT4yIO6gQO1GBUJcrQfjZ/zA=": {
            "valueMac": {
              "type": "Buffer",
              "data": "0yWyXly8hokOjhgw9ICK2demTjwPswqCwB2LgnXnZWA="
            }
          },
          "6vlvlP1+We4eE5b3MT01KOa3LqUH/5ahzdKcVLe4Rdg=": {
            "valueMac": {
              "type": "Buffer",
              "data": "RmtxI1GVLe+QxEDppHmkdSFqy8MaqZ0mjIXWPMkyRck="
            }
          },
          "UP38L6S6lZvxO05YZVBwUiw/pLNAXQAJKUua08Yz4pA=": {
            "valueMac": {
              "type": "Buffer",
              "data": "j7TqAJ9jCZcZIZTxob9icYcKobweShLqjDsEJ+TJFqw="
            }
          },
          "PdmH/4jI9nMLxAxlDqTB8QtkzrZYHDlMBL98IHVCYSk=": {
            "valueMac": {
              "type": "Buffer",
              "data": "6h57mXcgs+RQkOLlwrwlSClXXkoo/VZzFEGVwVizaOQ="
            }
          },
          "3KdpU7bPkWErTws89D6qAeupfPKnt1SVgeydKykTAm0=": {
            "valueMac": {
              "type": "Buffer",
              "data": "t8ZBblYLXqFnwKdVumeI3MeU7N4fekzcpVv79jrJSA8="
            }
          },
          "l35IGydYVymZm38doFwEH/vstsAu9P4l0nMWihGnMaE=": {
            "valueMac": {
              "type": "Buffer",
              "data": "DjFcXyF0/YaYoubsX31n3JLw99VJramTYA8YB020qW8="
            }
          },
          "wh8n++Zc3fh/Dceb12vTNy078uJHAUHf91iHWDz8OfU=": {
            "valueMac": {
              "type": "Buffer",
              "data": "Laq1agTD90nuzh1MU4c1eEdpHYCP/zNcU4pkXNIMaHg="
            }
          },
          "TPrn+7ETxU1xfYpXjYRolqkVmPH8mca4YnDhhy3A3s8=": {
            "valueMac": {
              "type": "Buffer",
              "data": "33lpHFXmPV6bm6YCMcLIdDh9efZMR4Zp7areySQ8awo="
            }
          },
          "3TEGiYESP69vgzk9F84eLSV5CP8eiiOZkdFXy2aGvbo=": {
            "valueMac": {
              "type": "Buffer",
              "data": "VJXJ5fcJZVh+svTkHw3UA4vo6Sj2EvaPNToG5A8vTTs="
            }
          },
          "lwJAiSg/X6qcrmpI6nPgL5KYTiCmRRP5A4F031T3x+g=": {
            "valueMac": {
              "type": "Buffer",
              "data": "PGy0cIe32Zq7zTqeMCGQAYnhk70BswY54mAOFGqzNC8="
            }
          },
          "UGmX95XmOMRZB7AHKK62VM39vVbs5oYmqqvFU6QyOac=": {
            "valueMac": {
              "type": "Buffer",
              "data": "WunsK0/ktLx1IoowhmRezqHI3enFYN/ZuzNqCUbUl0M="
            }
          },
          "nN6FiRMv6TpmxgDg443uPnb+FtyrAJyWflDPOtnjJBA=": {
            "valueMac": {
              "type": "Buffer",
              "data": "7E6YIBZStGG2RRuqI+zSqOqEIhT2hSqD5Rpo9/vcc0M="
            }
          },
          "njlN5Dk951fqqTmeerLMFTbqRYrrWl413WpU6qU+iyw=": {
            "valueMac": {
              "type": "Buffer",
              "data": "SwaUdIX0tSAbQwG8zWyXRXymot2rr8LXks7wTKgJxcg="
            }
          },
          "GR63h989WOzKCHK0GBwizirWk7wNHs1YVZj2kOKWGPM=": {
            "valueMac": {
              "type": "Buffer",
              "data": "ta3yrCAJqHoGSOBR1kzAGh1yrhfdwVGWnbikEbf6WZs="
            }
          },
          "PRPpfsLPKbgYXasNjrYIVYkNV0MxJK51BqKePAJ3EFM=": {
            "valueMac": {
              "type": "Buffer",
              "data": "w7Q4enNEgVcnwPJtwW1JP2p1TOLd9iFVAH0ALzOOP48="
            }
          },
          "bNCun8mF3kzRAN5LbidWpuROWYzP9NfgtmvXxNc5hc4=": {
            "valueMac": {
              "type": "Buffer",
              "data": "nyZPMmfIpBvlYiR8d1h2HkT5dknYUwvBZ0EnJi3u6kg="
            }
          },
          "TWgctx/OWiLN/vrZDUeOpAs1PvuUNw7+iVxF9LTv4fE=": {
            "valueMac": {
              "type": "Buffer",
              "data": "5h7Gae/+i0JTzu9qVg3GFlBsBy+f3X81Jp1TWl7N5z0="
            }
          },
          "z4Z1dzmgV4CmuEJ9e8x7N92Jtzs2OU+sXcopA7PvoOE=": {
            "valueMac": {
              "type": "Buffer",
              "data": "EbywTdnl/VreWyQNXzY7QoSbo+ZWfmNKXprMJdyYbg8="
            }
          },
          "KotK7w/oS8tNnbqU1qjiieyYqNM4tJXe7QDwc/ys03o=": {
            "valueMac": {
              "type": "Buffer",
              "data": "7rFf5NNqhVnm0aTci81zM5KouvTGbXtFQdHCSPUYYPA="
            }
          },
          "qX8CRVDUkCpvdnxrpYPNlYb07Elu08XsNe2En9Lezvg=": {
            "valueMac": {
              "type": "Buffer",
              "data": "8m3XfC87CBU/AtPddTp8KXBZglkZyRmlYHbilsrZQxQ="
            }
          },
          "a+jBs6IoxCqVT8TTSfBVUXdi+aRPbD5UaSvbVVB3Yqk=": {
            "valueMac": {
              "type": "Buffer",
              "data": "QGzU5/aoj7rWZKmWY6PY3Y7uEKXOJzByKM7zDRE1XjM="
            }
          },
          "VA0ZtUrnDwzAOHaCiwz6gZVinypJz7ZYYD/kCBFVgPE=": {
            "valueMac": {
              "type": "Buffer",
              "data": "BQH4FC/s6d27glE5SxWxzVNVgSb8PbcjKtOlq+2/CjM="
            }
          },
          "/75xs3cDhHacYXK6Qxu+e0spOk0xA0Ab4G+1knB7or0=": {
            "valueMac": {
              "type": "Buffer",
              "data": "hp9MdDcTyllJrks8kha81WzF/WaExV2iYip/iX11sVI="
            }
          },
          "GRbAJnpudOjvdJidJKZXhHDzDwZiJTlxP4PtIelhYlA=": {
            "valueMac": {
              "type": "Buffer",
              "data": "gRSpVBnymrMdb4aoDtVfmBNp0cID/naMSykpo75VfTM="
            }
          },
          "YAiq10cIh1nJv9qV0mQ9eF71ORaKCgTz6AnS6By/3Wg=": {
            "valueMac": {
              "type": "Buffer",
              "data": "m7iGuJpva8EOOnfu93savUNsOxjcOQdXTAoUx2bW0y0="
            }
          },
          "3bW05sgxsWJKnzeF0C9FfpuO6veDaew6XU7cGCu8PmQ=": {
            "valueMac": {
              "type": "Buffer",
              "data": "B6GkxiU4VHO0lF8Mk/+xV1z76FhOLpzcQ9484ooa9x0="
            }
          },
          "rkAA/tM8aoJDVOrnh3Qlb9b3Y2hKdqNnCVWrZy9TEDk=": {
            "valueMac": {
              "type": "Buffer",
              "data": "9Yib5J6rWVyJ/RlD0Oc/ywcVEnXWDfzEsMUtswfcxHE="
            }
          },
          "ugu0lTMp5MIGUWM3ZUHg3soxSHbsqd2WS1swZAI/Ucs=": {
            "valueMac": {
              "type": "Buffer",
              "data": "52Vbkp/N6IaQyIld+zSUeKlzUEE7TZPN+cmay4Wfuw4="
            }
          },
          "PzQ69CEqA+N1Uv1pjv02LPj2N5YfV2WRFr1NNppWvdE=": {
            "valueMac": {
              "type": "Buffer",
              "data": "31eFyrKvXvlYBBhVJQU4w2lXavc50SB3okb3uODMEK4="
            }
          },
          "s+p/zelJFBUAji8tdvqKs4Fw9mcbvYgNXxHjVub1S1Q=": {
            "valueMac": {
              "type": "Buffer",
              "data": "JDdWVcFuTHCzpzDVRwJH/TREGZZrcgDMIRSkBgPjK8o="
            }
          },
          "WdUa+Srm8O3dUrs0QYuj4fUVTC80Z+efDGxy0p/62XY=": {
            "valueMac": {
              "type": "Buffer",
              "data": "nQ012vFTWfVvkhvZZvT/ZXIdpWBQ9D4V+Ys4Lf1Yu14="
            }
          },
          "wS8aZzsWi/gg1NLf+tO8OrNO8iVBusfk2fHmvPpjuo4=": {
            "valueMac": {
              "type": "Buffer",
              "data": "wooD+7HaP4ELo/D2B3nFqan6wXWUq8s8wBQl20vEc28="
            }
          },
          "4mH7RLY7TL3Q76WqVqbsswOTQVTOHu3a0fhaM1uBtpQ=": {
            "valueMac": {
              "type": "Buffer",
              "data": "aHIi/RpIv6xG0NsuQh9GlgeLbTT/hcHaTWoVyLaiAGA="
            }
          },
          "0WHXSa6jlcfTov+QO2BoAmy902dF60aiyi3ag4S6SEE=": {
            "valueMac": {
              "type": "Buffer",
              "data": "/oDkZKxElXXeTtzrR6EYS3pkjdQ/58UORYsxKkDpIiw="
            }
          },
          "W4JV8f6DAR9OJ9yBiWmQheJikWFxnU3OZIz/OaMy6AY=": {
            "valueMac": {
              "type": "Buffer",
              "data": "7QKkc/PTLvKKznpqWnyPxIL2QR8vCp6yIvonccGP3S8="
            }
          },
          "6QeWqurP/O0f2dVRQJsHJ6YVbJeL9Tg9o3wk7ofhVrU=": {
            "valueMac": {
              "type": "Buffer",
              "data": "L5PRStC5srsDUs11m8FhoMNhoC/Ol9K3Cy9i1cRjMEc="
            }
          },
          "r2d8XBvoWGW8OnmGecXTGOFwViZpJEU/VZbFLYcFfFo=": {
            "valueMac": {
              "type": "Buffer",
              "data": "TdPcstGSpJ8S0bFmx6YTzY3zvlU+ozHFw5Dg8SNK+4o="
            }
          },
          "sHR616Xc2LXOZoa3cieEarBWfjTm38No7gssNQSEdJA=": {
            "valueMac": {
              "type": "Buffer",
              "data": "NSjhbFmaCxVtrk27hXIs2D+qShZGK8t4CE1T3WivaEc="
            }
          },
          "2NUnCzCPFjjyDbx+KGpBkrB6CZHd+z+BfoKsQVhQU+c=": {
            "valueMac": {
              "type": "Buffer",
              "data": "hIyrKHqrKXb7tCmcftfPFKcLtNlkWpcjHJYIFXEoNOE="
            }
          },
          "bs+DQCpYteWsbWSemRh++82MabFRWCmUhFL5rR13FCI=": {
            "valueMac": {
              "type": "Buffer",
              "data": "MLgNJpwbnbMnUd6eAXYp8h7bSbrz7S4vyVbd/HlXsEU="
            }
          },
          "FB5Gx54ptVGPoyEsKIdWp97Vl16B5X48oZ/XBhI+uQM=": {
            "valueMac": {
              "type": "Buffer",
              "data": "FQ+G1pESsK7hS8k3IoZqX82YRw8PgxX8kKr/nnzLcC0="
            }
          },
          "zYOtKCxl0D/lmAiZK7nmv1/sldynTE+pV7e9ReovI4s=": {
            "valueMac": {
              "type": "Buffer",
              "data": "hqRjZsH9m76XONgW3i8IpYOjuu+/Lrh+HCfFoto2Rts="
            }
          },
          "vQyPqCHPj6vXP2dmv3vaJXy8yaeBys5mNq9yndQChvA=": {
            "valueMac": {
              "type": "Buffer",
              "data": "T8qBpaxzwaSZzFi5LZM6zuIrPhNqngxZnVwlVsjRwFM="
            }
          },
          "7NOdt3x1vfDfFKbBRVhAhlyVXtOdOQxuMZo1Fam5XUE=": {
            "valueMac": {
              "type": "Buffer",
              "data": "ZjW7fawXYy44+Ot4wHNNYQEuVW54rO0pT+7zl4hwjW8="
            }
          },
          "5hknZbuc6wbpNRrvdCxJnqA7Vpjp1u2bMvaJnMz8KuQ=": {
            "valueMac": {
              "type": "Buffer",
              "data": "dIgzTUSEjRl/F1QoUkzc/MRFT1+kooH4rEYvALaakjg="
            }
          },
          "V8D3d40ieXV/DXWLoU+dKWpivu2jAP9bTpsrixLasZA=": {
            "valueMac": {
              "type": "Buffer",
              "data": "kW3n8FxNMcv/XCJvSKLam2IpArfYMkp7iUvqs2u7f4I="
            }
          },
          "OfHydoDfbm69rjuJZtZGCNTAQxVoL0+W+WbW4sZiGBo=": {
            "valueMac": {
              "type": "Buffer",
              "data": "w52bbrOjGmCl3rZfmqo2wKlv7DFimw9sWtt04qu71OI="
            }
          },
          "QZN4NRs9mD1/J11e84T3oG6zKzkZewAmXC0D2Q1Tr4I=": {
            "valueMac": {
              "type": "Buffer",
              "data": "QHOWDI6cIHxpdqv64jUsTPoDChh89fKPZUGdiLapyWw="
            }
          },
          "vE+4ZTkByv5HjYVRfQNCjCvoeqtf0I5ARV9osSgvuZc=": {
            "valueMac": {
              "type": "Buffer",
              "data": "JwidDIyM93Rf8k7g/eraosU8pbBmJBflBBSrPkq6kAI="
            }
          },
          "gcPFqb1hjooYKlDH/cEGfxTZlmSZVufR3dkyBcdJn+Y=": {
            "valueMac": {
              "type": "Buffer",
              "data": "3M0X9AZ5g0QSlfng4PRituKHvSJ/2hAPEsoAzNht9lQ="
            }
          },
          "ePjrFGTXPIIjxnF2OoI0NBIOgCivfANO2pfy+ZWstOY=": {
            "valueMac": {
              "type": "Buffer",
              "data": "zIOAHc9/UvIxaLEvEOdC3Jq/pOBQYGL3Z0zvm+4nzKI="
            }
          },
          "12dJRzAXzEi8f7u6BbkMO76BQcmqe7ry9W97YK6z6tU=": {
            "valueMac": {
              "type": "Buffer",
              "data": "c/mKZfN1jIM3hMcSF4mFZil6YYokzIPCG8fJP2j4u9I="
            }
          },
          "MR/74mhUldZZp9Mtq39TQKdgE5oPXU4izhVU9c/MSpI=": {
            "valueMac": {
              "type": "Buffer",
              "data": "eGBHkZV0DwS5dgbZKhmpcgx6KIoogjnujkVqJtsoQdo="
            }
          },
          "IBIxlsv/wwZD4e1DRpHjv7XjbzMZRmjpGTNFimBDqUE=": {
            "valueMac": {
              "type": "Buffer",
              "data": "eGQGM2T6nvvjiSB4XNDW4kh/OjBy1DP8QlOSQisH+Vs="
            }
          },
          "xcp1xjSTQyUZ+jKeWI9YQIxlLqIofSjmTpc70fhJSQc=": {
            "valueMac": {
              "type": "Buffer",
              "data": "Ob0GSfsE345MEQznll6NhcibFNjYn492t0hNGOXreHo="
            }
          },
          "5oI23cGiusC83MEERusOdow3LJxvOWxo+8l8Hwi85/c=": {
            "valueMac": {
              "type": "Buffer",
              "data": "o8qF9BYyO2MRlSiz+kDH94vADpFHntU5WupCk/yvuRg="
            }
          },
          "DA5z9Q81KvBDHyEwF59nRCnjkeIt/cCaWx3rPClJ7vo=": {
            "valueMac": {
              "type": "Buffer",
              "data": "DEUzfC9HYEq9sUsa9EVZsTVOlm/dR7LpNOtvZ3Af0mg="
            }
          },
          "R9g4KHJp5vMuUQTu7DSx5vVWnK/lapc8eiuXKoCDnC0=": {
            "valueMac": {
              "type": "Buffer",
              "data": "xe1DlwsuiGt7AIGtAtnWxi7UyzfG8itiDYKhvaKZ9ek="
            }
          },
          "JT7SOUrOCh7ETLJ0dmiXvMLVY3nMYJtf35mvcW+JKm8=": {
            "valueMac": {
              "type": "Buffer",
              "data": "vhqE0J3PdU9iDHWFHh8v2YqLd27iMr0swP1q1sYJ/3o="
            }
          },
          "Syzmtf8BvQvMbRtCIFTbGTKECERobG848wjOdj3W7a8=": {
            "valueMac": {
              "type": "Buffer",
              "data": "TBYwF+MQhflhz/1fUyKwIJXqtfJ+YIs4V3UFDi36oEA="
            }
          },
          "iABj7eEcVLes7bnDpFlXbCPwEznlrMzdLBZ4iTU2/j8=": {
            "valueMac": {
              "type": "Buffer",
              "data": "EFin+hIPewRIHQPDF1/babCH097PS7kejDKqOAK58GI="
            }
          },
          "WWfnWWYJlLZTp3D3xVtrAOxfSjPmMxuQIpHDjNunb2I=": {
            "valueMac": {
              "type": "Buffer",
              "data": "Wh2Hr1RvZDAvylZR2jb99q8+2J+96K5qCFpyfwDzAGE="
            }
          },
          "4HVIaTNTzLUIavPstyj8LZ6zMsfDh5JCMlYKVpevuc0=": {
            "valueMac": {
              "type": "Buffer",
              "data": "xolkJGxaerC9/ByYf14HQRQPN1ziv2AucC/EoipMZ3A="
            }
          },
          "W7JTSsSqBFjkiLMJxK6I6JeHMF0maqEmjbcN5qFL9n0=": {
            "valueMac": {
              "type": "Buffer",
              "data": "Q0XdamCHHxw1QXLrVvDOZDUFODTJ+29obkXrdM435hk="
            }
          },
          "rEFYAyyHTXWPkQnMAO8+0F3DOaCpaW2kmY8pI/HtmIw=": {
            "valueMac": {
              "type": "Buffer",
              "data": "1SDdkSdoNrOKXJTAs7/tcuglnE0fj8PyWX0IvYUozZ4="
            }
          },
          "2imwgddpmcRqPl3g1BgSJ2NE5txbKgZbx8ERqs13T8M=": {
            "valueMac": {
              "type": "Buffer",
              "data": "sCfXjFtEXPjLasg4P3E/7irGccQk3fQfS0zDHHCoNpU="
            }
          },
          "XzvE3yR1u18pPB6gxuTvssJU7Ho6xzi4XFaXVlFndzQ=": {
            "valueMac": {
              "type": "Buffer",
              "data": "TkH9l2Rvf+emhIvahOSz6ElNNHwaHcPLfQC0UJAIaeU="
            }
          },
          "l6PYK8Plichv+eq5xMG8hKXG4iDsChnd2BdoGSmFOCo=": {
            "valueMac": {
              "type": "Buffer",
              "data": "4NZKSiLOU94kbxWethvcYsYaOaJXSYlBHbhnfWaj47w="
            }
          },
          "/jOWUWJxXMnQqCkwZzVjz8N957RrGluCdDzP16yRRoU=": {
            "valueMac": {
              "type": "Buffer",
              "data": "/sf28sG6yyOi98DDYnvgannzOkkU79ipcyi0wOpVzEE="
            }
          },
          "b7892ge+tyLgZiF/reYDf7CqEvObinE8/9XyT8/8tYk=": {
            "valueMac": {
              "type": "Buffer",
              "data": "nyBLL2S1cXeQoscYNSQRTf1lg3Po7GJLeBxbmrZK2NM="
            }
          },
          "mm1/voYeMX6XEblIZ769FW54FTGwTHb31dmbmDLHLwQ=": {
            "valueMac": {
              "type": "Buffer",
              "data": "0pTc1pqenra5SF64F4BsROOG3qCB5fyMxdzF9ExsiOY="
            }
          },
          "gBFYUwAGsx2q3AemkZ385zJ0yaQ41+xuygXyJfNSXsE=": {
            "valueMac": {
              "type": "Buffer",
              "data": "HX3SaDAVTmndazeovsKAcVDZ1LqIoKTyzv4evIZkBVs="
            }
          },
          "E0KUacHH8OU5e8/52svaMgRpJqkHpHwixz4ql8X6Efk=": {
            "valueMac": {
              "type": "Buffer",
              "data": "Av5jlWAQFtscRfsysVSw0P5dy4zoCMIa5dEVwShrCkg="
            }
          },
          "0j9yPmmGQ8JHQFwbkHNaoqmtSvlpfEP/GgkbHSUk2XM=": {
            "valueMac": {
              "type": "Buffer",
              "data": "iNiWp+7ci9sjh8Xtlhb4W5RCySUVJv32bMA0HDnmUjU="
            }
          },
          "6EeKvZZX+fG45Nof1f3utQROGPF0ZrLXcBZRX/ByVoA=": {
            "valueMac": {
              "type": "Buffer",
              "data": "SJrdouTgWoAVW4B4ztidD3bRC6B1/oMUNTIrOn7D3Sk="
            }
          },
          "g6P+J6l54qkIv8sGFjAGbkI2SOCGXyB7/cV1WsM651M=": {
            "valueMac": {
              "type": "Buffer",
              "data": "2D1szD1M8nSqVzzO+1wFvVlWD9m7yoQtoxVbWXBaBOo="
            }
          },
          "RJiN6sZ1WZ0qJYepLQQ4Xej+tUa4r0d1oVq7YuDp9Z4=": {
            "valueMac": {
              "type": "Buffer",
              "data": "JNpAwNGQVMtFlr5jTC6ICLRtznW9LQZUWJspde8mgpc="
            }
          },
          "tu0GnMuMrrLZkAZjV8uc8BUtlJ7Asmk3vxTX7Vk9nnM=": {
            "valueMac": {
              "type": "Buffer",
              "data": "xTQ9xnsfLUKP4xfUly5gbGU3Qt3lZYEvD7yRPokVwFM="
            }
          },
          "/XPoUa8v3ZMxIUBuRi06l03lQg/QAQY/TcjH5L2Uyr8=": {
            "valueMac": {
              "type": "Buffer",
              "data": "NCId3l4fR03B2JrBKZelpmfZBOt0SZjo0bSlhSY2I2A="
            }
          },
          "cUuNDlvhR+UQCtza6kBacTcPz9z5Ctr/BBpbXdV2/O0=": {
            "valueMac": {
              "type": "Buffer",
              "data": "rQbyD2y+7N3YSRw+2H2xhIH7Dfw3+gpCP5y1Oi07OGc="
            }
          },
          "G5QNKTxJY5iAx7janoSW2EamSVW1ekvHGZjXf9OYao4=": {
            "valueMac": {
              "type": "Buffer",
              "data": "LrTrRg1zF+3WfbrmynkSSzMbDB4xlyIkkTEqiClh5gc="
            }
          },
          "/t0zAiqjTtiUolPwUajlYip550NO79e8kJKppVPyXe4=": {
            "valueMac": {
              "type": "Buffer",
              "data": "O4Sm2ITA9m0WRTyCxfI7Xfm91AUc9JeecCY5IHa/M9Y="
            }
          },
          "R1bq45K4wcG1F7DThiJrKYSOS+o/gbs6dmkwlPfZPVg=": {
            "valueMac": {
              "type": "Buffer",
              "data": "JrGN29WwRAHriL77q9AsztsFEsZIJunaN/eH8ObFUiI="
            }
          },
          "uej/Gu12Rst8QphxUMbeCFTBdlK8auO4t2V0/Zdvpbs=": {
            "valueMac": {
              "type": "Buffer",
              "data": "jvz7M7kt/FV99sOhL5U68n7xo+ULPcWL84pMozczg/8="
            }
          },
          "sj3sNEHtzMyRkHLZztU8fwHlKVU8QWnWGX3NNedi4Gs=": {
            "valueMac": {
              "type": "Buffer",
              "data": "fx0WMAPsZ/MujS5DPw/CmfI1IF4y+NJgNG2VW1yHsvU="
            }
          },
          "DqLTisRAykHo7t9h6Roi9maZxKqmdNLFZ7vU4Le/DkE=": {
            "valueMac": {
              "type": "Buffer",
              "data": "KNlPHkVVXEp6LzK5C4CmscQiDFa7D5CMUCOkiCFffRQ="
            }
          },
          "ygen8gX4/AIMvLRNdkifK8PTjU6I66Nmj8RxF30BGw0=": {
            "valueMac": {
              "type": "Buffer",
              "data": "g1/Uq7Jzm7gZ/nRo/x57lTkYUyPBe8b5/aIg8Fsocxc="
            }
          },
          "onASVUnuyOZs9C8JOt3yRsoXlGgRyxRxJ4ccCpaSdtI=": {
            "valueMac": {
              "type": "Buffer",
              "data": "VxZkm7eFPHavyjpfu1yV4jCcVsErMg/Xx+D/OPbffwM="
            }
          },
          "voGUZROUU0aSMBfn6NjdSkoMNee7+7lml/Dqw5YmrC8=": {
            "valueMac": {
              "type": "Buffer",
              "data": "ONe+H1TLfZaU6cpIUk3+FvL7R0d/VfDDV/fY1GsG13o="
            }
          },
          "WO3FswMat9RGNsek3ghNXiq3pIxSCZ7kj1jKqIGCreA=": {
            "valueMac": {
              "type": "Buffer",
              "data": "uJ7/9e0CVpWBmM2SnpRCjVMDWlekUX5Gl+DVU7wGZcw="
            }
          },
          "vxZfXLrKNNx2hPVfhWUxgHrnstizOaC7H3KXCRd15HM=": {
            "valueMac": {
              "type": "Buffer",
              "data": "IdOuUoZdprC3uKFmX6odscAKfUDgPE3Jvqkx+mzqnfU="
            }
          },
          "8gsFJrFP49zd6x929oj3mWRug6LUGhu2ihYY570N2aA=": {
            "valueMac": {
              "type": "Buffer",
              "data": "SGMSWe1Li22awMpkssYGdQrFAG5HvspN6XPziE9T2Ls="
            }
          },
          "qcEPLdE38yG1owhF2qjWsEDLcAdSjm1KJm+i+5WB0hM=": {
            "valueMac": {
              "type": "Buffer",
              "data": "eADwYHilO/sHcnvK6JJuRbSxV0OrobY4RZGSVpfaP+c="
            }
          },
          "KhK1abD0iAPWnXzVl9sTTKaMmi/mBslriQT1N+wpsZw=": {
            "valueMac": {
              "type": "Buffer",
              "data": "qUVDBkjVbKpbz6LXTxy6slREMsEzotfikNQtkB7w38Q="
            }
          },
          "Mb0G+rM8/S0/J6CziM5On8Yq+mQeDacOf842z+LXQ8c=": {
            "valueMac": {
              "type": "Buffer",
              "data": "5O/3K4u3a/TxaDQfnZ3Q3EDw/NJPBknNgGIdkWQbsb0="
            }
          },
          "uX2Fwaa7EwW9Yo+b0EmlcfaAADfojVpJbpl2mzf/0rE=": {
            "valueMac": {
              "type": "Buffer",
              "data": "VgCQeXKCwF2pHnWb8NWiHcTz146XgmvZpmJo9YGXkJg="
            }
          },
          "7Tn37nOVhWpbThs72fw9EaceXcPKMkxBP9IjKDdZFgo=": {
            "valueMac": {
              "type": "Buffer",
              "data": "UsvsIkJel5jtvSXXtAT+k23fZY3ZTt9JgkvpX9Ys2RI="
            }
          },
          "2cu/gh/Jg5zFKl/M6Q1liag4SiM0ekgQVAUtf9DjQk0=": {
            "valueMac": {
              "type": "Buffer",
              "data": "XWe6Cwgu4QOpQtZ1rvvsosx5yBV/YadPYYVl+4Doe2g="
            }
          },
          "XpQxBC9wUy4D5XX0HmEMPKFocSaZauGyMI31xZ8iv7Y=": {
            "valueMac": {
              "type": "Buffer",
              "data": "vXxxTmn0w+oZJwLx/bx9qOuaDXM1FIXdkQydQk75tQc="
            }
          },
          "l9mu2CagCxt++B0tUb+zmaPXVDkXJ4ULXPxZ/5saYUQ=": {
            "valueMac": {
              "type": "Buffer",
              "data": "l32qdJkL2PlfozMM5CR1ESVJqxpDM6ZRTpXMcVJKzIA="
            }
          },
          "vuIoDdbgOLnH/t21ioO07HkPefkVaKBePBiENxVHRyY=": {
            "valueMac": {
              "type": "Buffer",
              "data": "ouk3tnBPkztwYnTF8qBVXEJkOyEL7QyDprbQRzFNM0k="
            }
          },
          "urUfVMtiOuHH7YbsH8CdtC2oKjlQmKqQIg+hKCM3Uxo=": {
            "valueMac": {
              "type": "Buffer",
              "data": "xfNDZ+zxQbbBFNtqwZ4lRwrhI9nqgaNTo612vnPATX0="
            }
          },
          "MeFqJB478X50tbZiVTGC6TUJ7FhbjV8MTbWEqIyOHms=": {
            "valueMac": {
              "type": "Buffer",
              "data": "7h1ZOaWskZwlKa8L2YX3UtpjYt2tIaCSveHHwADu4GU="
            }
          },
          "xhC8xv+HRSyq3NipRCBl1szrFiTI4rlcgq9KxcxOIVY=": {
            "valueMac": {
              "type": "Buffer",
              "data": "FzrQGb2pUeNfoOHb7bkacpirvrojm5Rd/nXhAwo31pc="
            }
          },
          "/XlhONslv6OHqW+udLszDFK51EkXIbBHV0bJ4qkhuoc=": {
            "valueMac": {
              "type": "Buffer",
              "data": "gyFEPt+kjmSSxwtnZrITXtgrYCnzym8rMG/OQrYKsHU="
            }
          },
          "i50s0SDLHwQUjQwlCMy9/PxUKSbs83qBRXKeAsSOQuI=": {
            "valueMac": {
              "type": "Buffer",
              "data": "rewutuqwHHGNm23a4gUhyIMuklBjl9ULrzfMoKss57M="
            }
          },
          "+gVnfANahq95rKMEz2hPkBvfx0M40RPjo9cK1spayII=": {
            "valueMac": {
              "type": "Buffer",
              "data": "G6ovFYjMl812ozh2NciCj1kCYKiUTGRDEDWfIZ6HWng="
            }
          },
          "WFx9cTRQEHCtQ8RAc9FypxLVGzLPPpPWalPFBz3GDrg=": {
            "valueMac": {
              "type": "Buffer",
              "data": "9dkBJkOsSoWN8ukZpUglDg/GjG6axxM3b0MpGC0sC2s="
            }
          },
          "ZHrqem9VY1JNAeOKjt7wfMoAC6ajuaoRHG1LwReZodI=": {
            "valueMac": {
              "type": "Buffer",
              "data": "8hv5mbPf8/2t7oPRpphgEQVs+C3UMatbUg2ur2Zl2Ns="
            }
          },
          "zGmzo/pA1UCqLPcIoEjH089nTpjepAnEZx/XVmv+pGE=": {
            "valueMac": {
              "type": "Buffer",
              "data": "nplsm0xd11zBjJOFRIT/AghCmnj7m0BlEtYPQxduRtg="
            }
          },
          "toTCFMD9lUMW5HojBoNCX/4cVVs8PmZeeKS501MvkZs=": {
            "valueMac": {
              "type": "Buffer",
              "data": "icbfL6Ai9lwMYvwoZq3+FHh64ReccCuzCLomOrwJk2Y="
            }
          },
          "VkJdIp3n0+HqEFLnJaOh69c2XC7kEZ8GAJPTtDaUkik=": {
            "valueMac": {
              "type": "Buffer",
              "data": "QgAjcybGA3WEOtKkXL+54NOWi/XppN6bAD23nQvEnT8="
            }
          },
          "0JjZgX08I7Qtc8+dCq46CGfbl3OhYrBO6L0afhm0qZ8=": {
            "valueMac": {
              "type": "Buffer",
              "data": "r1WEobxnalqhYqZO/VvYLIyC09/xiUBpFvpwVoFhQbA="
            }
          },
          "3WpHcJcZL8PRluQpg21O26UXvGF58fQnwYXPusUBoC0=": {
            "valueMac": {
              "type": "Buffer",
              "data": "EyZVTCxwW1s+phwKNxs5ws9/CczhEt2jwiiVp5EtsOQ="
            }
          },
          "xtkKrdhCZ0c29P/51DXeH+i04eg/CV6pTKWdCJVfWsk=": {
            "valueMac": {
              "type": "Buffer",
              "data": "zZXcI0dfNZklAsvZbYSeVhMGgcb5fblqyB3XFIpbwuE="
            }
          },
          "sEE6GQeYeIhJLKeCpdlVAzF+P3/or+0ZPWW/GoFqokg=": {
            "valueMac": {
              "type": "Buffer",
              "data": "wnyYMAqc02aHv4yJ3ppw2rqvlOtS5/Jgg034srhbx9Q="
            }
          },
          "LQjBXU6tYgZGuJ2utcJQtS3aTTLHeOhgyY6Sd3s/1VE=": {
            "valueMac": {
              "type": "Buffer",
              "data": "GRWJa90I+XlGQjlncHYCjOHQ3H9kldEZY8vpufO9PqU="
            }
          },
          "7iqUqoJJ9iTDOz37O+Yxcq8Wmacl/LuTNbfBGMpvQJs=": {
            "valueMac": {
              "type": "Buffer",
              "data": "KeleiA6GS0idy4fNqWcxte9TjjY9NZ+V4Cdop6WHr2M="
            }
          },
          "DLxghnYixnZ3gNoQULofJX6mDavEh2d2Fg5wiw5w8a4=": {
            "valueMac": {
              "type": "Buffer",
              "data": "zKNFyR/UqL+aryeAxXyvmgCsMHLBnJhwBQLuwV7r0jc="
            }
          },
          "0JYdy6gcFymGyeJXdPBHHUmYxl8awSltNAdbh0Ig8IU=": {
            "valueMac": {
              "type": "Buffer",
              "data": "2355qqBxvRHQrwW8vBz6DCuUq/ZMQECdndyLuZ2wIYk="
            }
          },
          "47i+IZAqpvefiTYPuFxugcqTXBxsNDnKNU5XJpXRL1Q=": {
            "valueMac": {
              "type": "Buffer",
              "data": "R7cDk8raROXdA1ZtXUnzKu3Tnlm4imq39ygNvnLJ2AI="
            }
          },
          "iRHz+BUMs7kHPQaAgXA2hUxg8eFbT7RBrOBfvbC+hRU=": {
            "valueMac": {
              "type": "Buffer",
              "data": "6v/rG+g+3RuAAxL4ldmxxw8BYC4Rh+6Y99rTwy3I9e8="
            }
          },
          "72DBZna9DWEPoKpXHRd40OX4fKy1CVN2XHiN2xQJ1vs=": {
            "valueMac": {
              "type": "Buffer",
              "data": "3XhYbWUZB5VfzhjV8cKcI5Qnp+BC3qqcHf+5MU2l5g0="
            }
          },
          "SxCTKi0b+BHHWHLGRJG7NNM0f5ufrVx/ARAbYcw71Rg=": {
            "valueMac": {
              "type": "Buffer",
              "data": "lJdTF8rY0yd062VBMG+S0Sa68FMkIXKmwwliSxaqTJY="
            }
          },
          "p81ihHOffzIaCgK4iOPwbuofeyXAKjJ4VNYNAAKfnfM=": {
            "valueMac": {
              "type": "Buffer",
              "data": "cl3H/ami7HBAH88rchOCxF9FMCIcPy0OfYO4k43HzGA="
            }
          },
          "AIBYSuPBa+bMqr9/MyOdD2qf39HeQfR9l4qnlfo5InE=": {
            "valueMac": {
              "type": "Buffer",
              "data": "hfDKaLnUXW1DCzvMcGgr7VA/QcJndXysEpF7dIJKYX0="
            }
          },
          "4GnRCGEIqGlcrn2chdPg/YjKmwC/SNib99L+ogcg7Lc=": {
            "valueMac": {
              "type": "Buffer",
              "data": "euMTFzAeFLUIoRYfNcJSq1GOnmDmyK56UW/pEnTT2Lc="
            }
          },
          "wL3JzqfhwPjeRdQ6E2fSnyozcoVq/XAipUpT8wnNe+c=": {
            "valueMac": {
              "type": "Buffer",
              "data": "evr0QVbfiV36EY5PprRw5iWHI4sizlp1U7Wy+tD3NyU="
            }
          },
          "NcCqy9a3sARWX8NYcjYc6y/5IOkiNZdU60EoTG3BDbk=": {
            "valueMac": {
              "type": "Buffer",
              "data": "GEV3gh03VRx3Z6zZvLfn7+RAstKKIOS/xCQlMpYGgBs="
            }
          },
          "hQSF8Yn+EVP3e9ihHvbZzAUkBuTappXOrUhMul6bQP0=": {
            "valueMac": {
              "type": "Buffer",
              "data": "87OS23QU/p/94ktrxXm+plnHxBYk8a6arAAtS7MNFjY="
            }
          },
          "NFhVXN+sJhgDiEKExcAW1U+JZuP/7mv3gk8HJE+s3c8=": {
            "valueMac": {
              "type": "Buffer",
              "data": "JXZ58GOpIDjRFbx1FbjCUkWTg/PyC6EtFOMo/AoqbCM="
            }
          },
          "Es92uh32NkKEGVoz3ZH0+jYq1ltEitx7QDmismGf4tA=": {
            "valueMac": {
              "type": "Buffer",
              "data": "Z/O/p4VX8/2QdqvO6IfMlUUZNSiie/akegFJLqFACWc="
            }
          },
          "CV35hjjLG6qxQ5JjcXMB4/nijua1SN7e7SG9J+8sS3o=": {
            "valueMac": {
              "type": "Buffer",
              "data": "BDXlMWVodaoQW74xuuIEvpwIVqGVJ1ZBsRbWUbzcuas="
            }
          },
          "PQzPkax3baJnY5F1+/d/2U+V7wIRtQDGKrIABttoLSI=": {
            "valueMac": {
              "type": "Buffer",
              "data": "fYEqcxAYRAp4uanhhMQggYhz70F5G2I9gtl5EXYN9Nc="
            }
          },
          "Lj4mbjsNSLv1BswLX7Kwrmb1jPmV5HRrTI4W5PU9qzo=": {
            "valueMac": {
              "type": "Buffer",
              "data": "p0B1wwwoe3u2SmbnJrQYH1H41RzhDooYFCedP/OM8HE="
            }
          },
          "J3aB6W5TLSN9cEe65/3+15Dq3oyBLBq4HwalJ57xZGM=": {
            "valueMac": {
              "type": "Buffer",
              "data": "JXULZ3J1fX7xPMRGGcASgoGJuR8VapFgxviostqN7Xk="
            }
          },
          "2q3cnwhGiuJDp2vCebm2f1aJPkdWfPfZUL9ErBahQ0k=": {
            "valueMac": {
              "type": "Buffer",
              "data": "dATvpTcovOy7SCXNRAl6/NLJ17uAFa02fMjNgx5vmH8="
            }
          },
          "BVr64AjTDGh4teIduEr5dyQehjnMmP6LyBmdXruXQO0=": {
            "valueMac": {
              "type": "Buffer",
              "data": "rc6K6Yl/z0i7TZs9pgSehYVUFzNxuiEsttRud7gmih0="
            }
          },
          "OsskXED0BeWOioOW1J8lJ+qsEL3dclh226j9r1NuqPo=": {
            "valueMac": {
              "type": "Buffer",
              "data": "RUrwD3ekxp9riqikP7DjKAfyiskygUeltm3IQB6bvtA="
            }
          },
          "1RlqzNH2qwPE6g9OvjBT90QPMushA5mQlGk1TIux9Iw=": {
            "valueMac": {
              "type": "Buffer",
              "data": "yc08ScObtyxBrVMmWY1XxQeDtEoNiRO67Jt3m9V0qMw="
            }
          },
          "JT9qwK5e/wbvhkQQqQ/PpvLyIBn67osgcPWabfsdDX4=": {
            "valueMac": {
              "type": "Buffer",
              "data": "GKIXHzK9ZNe/vnzflc04GSTupKt8qMVI0zpdo1UisvA="
            }
          },
          "K7gbaOEacAZCbcU6dyVyy0zyJZbM/EBPvqTksv/Mz9I=": {
            "valueMac": {
              "type": "Buffer",
              "data": "zPqD8Sbd3oYp+UZGon3IMPAx0bs7G8c0ck++IH3WFaQ="
            }
          },
          "Wq6N0CL3zt/S7ipwqoukMlNwCzKcrxWZV+W8McT81oc=": {
            "valueMac": {
              "type": "Buffer",
              "data": "//89NFlqB4NqBECXLiVMTkQMMJM6P2VdRR2ftybhSbY="
            }
          },
          "fJqSuYiirlDMOAK1fcWvsFgZonOcPDEiZXI9V5JUIS8=": {
            "valueMac": {
              "type": "Buffer",
              "data": "S5b+a0Sld9e28recXCHfcNmdos7tXai9pDcohXXWooA="
            }
          },
          "CkWlczgorm7EylmVdb4+MffUHA8sxmuHRg17bNmh+dQ=": {
            "valueMac": {
              "type": "Buffer",
              "data": "gRVZfaSe0pdVaQAsDlAYECzr2VZQR5M3PWWLHp/aFEA="
            }
          },
          "D+iFBW1mDwFmnP0B8yncKcjdK3DML1L6BWu29iFAnlQ=": {
            "valueMac": {
              "type": "Buffer",
              "data": "11iM9lkfRP52Ddl6qs29N1fcQI6d79ZFY+Q1YFSCf24="
            }
          },
          "zwo7/eivfjYwH3UWBzJmcsxWXv8CCw5e0S9ljAa8OPo=": {
            "valueMac": {
              "type": "Buffer",
              "data": "dqN7Be6q7Gfs40ehs48XwaQ87sDTa9MqoRBJIqB0nkc="
            }
          },
          "ESuHLs4aLLWjQ3iEib5L0PBwj+b6oLWK0Qf5zUkoigI=": {
            "valueMac": {
              "type": "Buffer",
              "data": "QK/UebNSz/oSgfcMhzZc1BI8VS6LKvvhkgiFq5EA9hs="
            }
          },
          "rI9EnlC9MDGHwrb6NSbOltXDW09sidycmxiMVcMPdEQ=": {
            "valueMac": {
              "type": "Buffer",
              "data": "fE3ITRlPidnVN2Yv8gjZB4riMShGiPTB7r1BIdcixOs="
            }
          },
          "dLcyrlYG4oWs/Z+9eAMtJgO2/bnc4KuZoNER4lYFp+k=": {
            "valueMac": {
              "type": "Buffer",
              "data": "jRkrV1lt2I0hFgJYL4maQtnMupqbd7U/cJpU4EyBAqo="
            }
          },
          "zREJpsUBher565N9t/2/psXDmtuSxUcc5YS+O2cB1UM=": {
            "valueMac": {
              "type": "Buffer",
              "data": "nko1/IRvbwhYaSUhr27UnBIY+WtkPbLnKqSk1euA0HE="
            }
          },
          "YkFcQUlduqUceGIejsBGJ70hAGLHpOaWLVJNZkUD044=": {
            "valueMac": {
              "type": "Buffer",
              "data": "f0b4so9zNgOFqt/WHsdEl3WPYrW9vVEdHZB73lzdIOw="
            }
          },
          "i8fosrWr09qSeTKtGZKc8WP9Q/N9v/EYqoyJY8eO/L8=": {
            "valueMac": {
              "type": "Buffer",
              "data": "Asb7IVd7v+pbA7Cl6fzw/Rw92n3XbsLiup3OmkKrclU="
            }
          },
          "vFhxVxQvo3VCfJPFgRc3dcIvQpEl3n8wHqTjFGERoBM=": {
            "valueMac": {
              "type": "Buffer",
              "data": "ojGHr/l0SqAVI2ik/DMhAHn6KqyhRGYVDkEONIfSukA="
            }
          },
          "PVkV0D6e4mv0TIygp6s79WIUcg/i7BkDYxNCKjApEHA=": {
            "valueMac": {
              "type": "Buffer",
              "data": "uhgDTbkuIbyOq8ySTZHJ09FckxSF/vxBOIcmcVG53ic="
            }
          },
          "KyLKn8v67vutJoeylUdKrA/QCTCZg5XT8Z3gLpRDW3k=": {
            "valueMac": {
              "type": "Buffer",
              "data": "vyJjnuJudyE9JCOxDMogncF00tYy68YkZ6fIN6jeBYc="
            }
          },
          "/NOQ9fnGsZC6TdXbfUH59YJUJHSdmSDbakYDfD16DMU=": {
            "valueMac": {
              "type": "Buffer",
              "data": "lIOcjiMk5Ie0hfwl9j9Y29KSKofMtFf6vkoq8Vv8u1A="
            }
          },
          "QqD+EDqakYh2Xgq0jkL2BJFplsiaG2oGe7tVMd4mOX8=": {
            "valueMac": {
              "type": "Buffer",
              "data": "rWyOIN4fcs8GoHWV1Rai6TaFIiz+kDmCIkwfXPUybyA="
            }
          },
          "31hN/wHsJZQF5USXDaZ5LAu8L41mu5NeDbVKFuw0nlk=": {
            "valueMac": {
              "type": "Buffer",
              "data": "LOZ8dZOwVZSkrJO0F/f9JNiQppxjfSyabx3zyZXVDog="
            }
          },
          "2dZeu42UJtNLWhlgJQUhNueIHN/Qlv1KxGAB+q0BVY8=": {
            "valueMac": {
              "type": "Buffer",
              "data": "NKZINYYYQWIqdqz6kHrCLYNacawDcdK2Zfy9J8DXUUQ="
            }
          },
          "Gpt+Q9O0PKJytMbxSBjMuoQDY3HI0nYk2Ur8foqcaCE=": {
            "valueMac": {
              "type": "Buffer",
              "data": "/K/Zk7UKZyblk3C6fRu11PIMRKnyR25vVkCwhZsEMHc="
            }
          },
          "Co+USN9fodbLqBXNiUiLat85Mz5YH3PMED1FrSb0zj0=": {
            "valueMac": {
              "type": "Buffer",
              "data": "BTezD6YYiRlnqK57DqfewoZmMY+i2yNQ3P1PlKJGeAo="
            }
          },
          "RkuMwyVBgQarVVBpTYB6C/Ly5Iosh1iL8XUQlCVkOVY=": {
            "valueMac": {
              "type": "Buffer",
              "data": "O7eBJTy4gmkbySyoanzBcdD+XSUl0Lel6vls3u/NN5w="
            }
          },
          "qZngxL9sdlhPzObLeqGQuMaiqh5AMylIQAJy0GyggWo=": {
            "valueMac": {
              "type": "Buffer",
              "data": "AquPUCApxkK7Gms1YgG3tvwfKHqZgqmKMyLlbUBaC9k="
            }
          },
          "NDy68I4dREVpeQ2bp5GiVKqLd9KCneyUbtXWqQoc2bM=": {
            "valueMac": {
              "type": "Buffer",
              "data": "67fE0eKC7fuFXHM91M8IEHaJAz6coHf43qiTon5sHA0="
            }
          },
          "R5J6mikKGN+Hkz3t9vK8tRw5RhzI1J0o1JMU6J1QQow=": {
            "valueMac": {
              "type": "Buffer",
              "data": "/I9ON1znCnZix5hv2C+x4UTofwlFekXdWVbCqtoYkvk="
            }
          },
          "K5xyrJ1ZmlD0xsq+wIyg7ITw8sIZjqUI30xx4MqL9Qo=": {
            "valueMac": {
              "type": "Buffer",
              "data": "MpTgTvM/RAMaMF15dH3AMUBTp/IlPFr3Dt5kIKzhd04="
            }
          },
          "9RTMUuTOJ/wlIr/3MWE34SbAxenqND+SDx1cD7166jw=": {
            "valueMac": {
              "type": "Buffer",
              "data": "31hZ6Cwq7nT9Nz/ldL2zl7wqkb0LaQpk4+6Wl/gD+nI="
            }
          },
          "MD2hQ6W60gUnwFkvl65Au9dxXVe3zPzAhaaOUQ4hGOQ=": {
            "valueMac": {
              "type": "Buffer",
              "data": "xriWYDOICh5fs4PeQbuRjp3wTMMDKQfvKkGLbfF7tbg="
            }
          },
          "w2DYqRCE9dS/MbvKYj8cvGeMEEOqNdoellvpmOWM8EU=": {
            "valueMac": {
              "type": "Buffer",
              "data": "SF2mYlge8sg3LqBjgASCtV2DJI8C4L0U4B34Q+EIBSE="
            }
          },
          "v2nkvzUFEUHDz0HzsOZ5FNk6JLD3yj6gwKyo0LOq2Lw=": {
            "valueMac": {
              "type": "Buffer",
              "data": "IjyUVyXDKvcby6i7y0yQLKjl30xIRKMtT5iyIUiDfe4="
            }
          },
          "bKcs/o6OPkYe1aJ2NHMKxRfU8rDzpzmXA1TI+Rswnyw=": {
            "valueMac": {
              "type": "Buffer",
              "data": "jg5sA2RPnRzOnacztoyi3QkeatMbHffnaE7MbgRPznI="
            }
          },
          "Upgh5i5r3vApiDIdqoHDEgUDUB++HW3WqAg3pXuaY9s=": {
            "valueMac": {
              "type": "Buffer",
              "data": "7o05sXtf+o7XaaalytHBTsi4h5bOoP2AkK7JqkUWhvw="
            }
          },
          "p30E8mOXEXqIJtnAyreVUpPBk8wqwOEcYWuXNE4RVBE=": {
            "valueMac": {
              "type": "Buffer",
              "data": "t+aTE1FA+UtyNWX5K5WwuWO+39Zqb95yGeNEJ+YVH3I="
            }
          },
          "AKo3oOqEn1r+Bx99S0Ye3MM+bUggFNt/0kD7dl1kt1Q=": {
            "valueMac": {
              "type": "Buffer",
              "data": "ltdASzJtm7jNH70Bjh7YoGci/G5C1L8va3a1VpqFyHI="
            }
          },
          "jwQqT2Bh/p8atHMFJGj+JSHFCRSjQnMf8aAQAzqWOio=": {
            "valueMac": {
              "type": "Buffer",
              "data": "GJYToeR2v+j4lr9ykshtjalcjdRW6dkaydAT0FRKJBg="
            }
          },
          "/3p2JpM21opqF2riNAuxayUtq0mKkGkFGH72oNpGXC0=": {
            "valueMac": {
              "type": "Buffer",
              "data": "tFu3N+S7XYuwKf0RI6lsew8Z3p7mg6zdfOpIExqjT2c="
            }
          },
          "sMfSDg6HL1udLB0aplgTcMu+bgBjeJVSG2qsb6W183E=": {
            "valueMac": {
              "type": "Buffer",
              "data": "+d4ZSjoKNPkmXtSmrVneDWkdZhwEI9uwHB2NjhgDqvU="
            }
          },
          "pzRhcek4diwkv4jf+3D9AyngHwmqAG8OI4RLkhIlPB0=": {
            "valueMac": {
              "type": "Buffer",
              "data": "/T6rYkrf/ZdgC2coWMZa9xcOuOaT5I5YDBHbqk7CA4E="
            }
          },
          "aPNaXJ0jKkbk7BamPDFhG8bJv5V0zyxiDWByMiJzGZU=": {
            "valueMac": {
              "type": "Buffer",
              "data": "VohO2huizIYp4bYR37Vyw33PfT33PJCmsI6JyAfE8Fo="
            }
          },
          "tbexbPgg7qYxqHXCk6P5bsU9xiwF0c5sRn1hMCaUJKg=": {
            "valueMac": {
              "type": "Buffer",
              "data": "GakqukLeYoFaTohaGROt0ayHEQt/UbtaCCCGBc5HpQk="
            }
          },
          "Wi0y9VHrGmRuQpRsNzFz9eckA3Ywi8gtp07UG2mma3U=": {
            "valueMac": {
              "type": "Buffer",
              "data": "u6HpgOlLTlwDSQCjwj6LKQ7AhVDOjbq0cJUqCD3n7FE="
            }
          },
          "ShNS8bZkbzetjwTG6zAF23z0+VtqdlrZ1rEzms472kc=": {
            "valueMac": {
              "type": "Buffer",
              "data": "z05JNlYXSj3EfLACaIXoIMAXI261bqEj79mlYKyS+w0="
            }
          },
          "rKhlvLyiu8RNK5J+0lEoieieKsLHnQhjAhBbyCSpaAU=": {
            "valueMac": {
              "type": "Buffer",
              "data": "Qsxd3wbS1Kul9Kz5YMF1KPlI/OSTlTd3n7aGhZVKDuA="
            }
          },
          "CjHM9IHjiYuTI62C86z3kNEljJ9P1B2oPpMXeyWYwgE=": {
            "valueMac": {
              "type": "Buffer",
              "data": "x0cE97FC6cgScgmGEu7FF7WSTrr7+lv9wb3DBxL7ijs="
            }
          },
          "5aI5BqJQnup+XExrgIHYddtOk5CKmrl7QUkaVHKQNhQ=": {
            "valueMac": {
              "type": "Buffer",
              "data": "SiGzIjhyPsufjRSx3s21MI4EwQnW8oer4vMMIrNjvN0="
            }
          },
          "Kmo29AETu+Fc59jt9J4vWHSlpWSs4ppZyD/ZhOT45Mw=": {
            "valueMac": {
              "type": "Buffer",
              "data": "Ezh5lryveP17hg+5bn9jXYf+l6kXsKTNXcMV/4wlJd8="
            }
          },
          "zWIi00Qn3Q2CtRHGLPz9lFC9AMv+ad2NGQqUL9+msf4=": {
            "valueMac": {
              "type": "Buffer",
              "data": "1+dxzCkYQOFA+HXzJdend5NWwi+oBIJMyW5fzQ6vUGw="
            }
          },
          "VpdbBmSy7wVdOYNWydUMHOUZiQJSZOyrxhhs3wJUlTc=": {
            "valueMac": {
              "type": "Buffer",
              "data": "B7pPC2GilxDTGTuzpJW0ZrmcY7M5866HghTBvOTu2jA="
            }
          },
          "cFy3+mZNSgrp6WN8xlst608W7Y9HG50GTcKhj7R0NOA=": {
            "valueMac": {
              "type": "Buffer",
              "data": "AzWChYawshfc5OJZAzsh7u8vCjCsn9LkddGb+PfP9AY="
            }
          },
          "iOhYLzZeDeDc94uF0mohIqA33rX+zExcfqGjboQFFHg=": {
            "valueMac": {
              "type": "Buffer",
              "data": "y1wbrhhP+9Owbu2ZNJVGjL4a9Bzy01F0rpNrZdad4+g="
            }
          },
          "GYU70FsgbyoAgzEvmImruKF8JaApWBN3ngZPd/6t3m4=": {
            "valueMac": {
              "type": "Buffer",
              "data": "FgbJ6Oahwp38enU7fGTfDjkMt06N16rX6393HWQc5S4="
            }
          },
          "DRaDVDMRBbj+hA4Be+Hd9pe3OGfeYkALvC4brdoD8To=": {
            "valueMac": {
              "type": "Buffer",
              "data": "gOzx2QI+5ac9+WXc1p9E9od2E7lDEZsPk5gLQE5M6jU="
            }
          },
          "ruw+dPeO1Me0LBMeXHylKliHWXBNGFdS7EKOnH+cPbI=": {
            "valueMac": {
              "type": "Buffer",
              "data": "2vAz6HKN1xD1b2apBMPYjzKF95bcAKBTePSk9+7UO1M="
            }
          },
          "dgLota47mKYwiGu2W7QMlY3N4mRCfdm2J5UiWQ1/p9Q=": {
            "valueMac": {
              "type": "Buffer",
              "data": "1Rz2zTRal4zloACIWtsG4c3Kjw3pyXvxWTjrU64fLuY="
            }
          },
          "PalK+EL6JYiATdWGDAh4YWOahfXCqVtpwoMZSsiwwNA=": {
            "valueMac": {
              "type": "Buffer",
              "data": "vxbvPj9BTe1OLY3yI+C8Mgg1wYxqnUK+DI6LwCdg6Rs="
            }
          },
          "+zK++CdinBmLxXHaLk2jww3yZ7UVRIgK3k8l7a/ZDf0=": {
            "valueMac": {
              "type": "Buffer",
              "data": "Wug9Wl7XfwXQ07joTk+iBRa0eylX9bQ922t2E7k1ZQQ="
            }
          },
          "w1SBmuSpZuzRa4yS5ad6CyzmzbV/nuFsVkVLZwUQhy0=": {
            "valueMac": {
              "type": "Buffer",
              "data": "B0/L2sRKLHMIrVGLIILdB0vZKfRHfRkSqSySQ226drk="
            }
          },
          "c8phFh+09SLKfHopJJKMkSZeHnY9R8HMjEGWIFNNtmI=": {
            "valueMac": {
              "type": "Buffer",
              "data": "ZgkUxWQS58jezT8WCpwOzPl4SAqpjdR/McEuqvSG1Us="
            }
          },
          "jiSpkLDHoYajqt5kcuwyPUbhv5W+hI87Jy8M3wbi+o8=": {
            "valueMac": {
              "type": "Buffer",
              "data": "Zscx2eGL+IAzp5SlEadvzInPhN6Vws/RCJIo4scbcRE="
            }
          },
          "Qtv18KaORPtOZp+T9qrEFzjv/urZM3ScNvw71RTYwl0=": {
            "valueMac": {
              "type": "Buffer",
              "data": "jvHc6V3NK84nd4TVTj45PjW1WXlUqSsb49iNwzPg3jo="
            }
          },
          "N7+9zweXmD6rd4arJbAWotcfgBBVh14n08Rwy6+rLxg=": {
            "valueMac": {
              "type": "Buffer",
              "data": "XNpJVqvyBUqJEOKMdbdWLDSD77Cd43YDaOp6m8g6woU="
            }
          },
          "BbsuLNxhj/r0oedauPVftHD1Vjmro37lCCMbntI2bOM=": {
            "valueMac": {
              "type": "Buffer",
              "data": "0MYD2LYDaD7tTS3ajYULbW/qxawHlxpL1iCHuYdoiNA="
            }
          },
          "0yCUcpIp5zrbTvqdlFX2Wgc32ioqm5lhT9qYh6p4jXk=": {
            "valueMac": {
              "type": "Buffer",
              "data": "1tMxBzT0TfswBQXSNnov0JqmkpZzkDm8WRYEEuLVJjc="
            }
          },
          "REiRjCPORPrx7R5N0hELz4jzpdjoXbjZFmFGevgt7UQ=": {
            "valueMac": {
              "type": "Buffer",
              "data": "z3zu1Lw0vM0dWzhPpA4LSvMo+mfC9r9bIvM7OfbDLOU="
            }
          }
        }
      },
      "regular_low": {
        "version": 1,
        "hash": {
          "type": "Buffer",
          "data": "M+ciFE/OowyzwSNW0Vl1szlwce6VL6bHfBhRLRPJQdk58bUlyg2ISk+8OLpvCAAVDq6THYUrK9rm8esTPVn/pxuOMu+gAldpxfb3KEHOEkwjr4pxWDaWYQWy7cvxnX1aw51aRUgtoFkZjoFGcT5QJiG2B07sJuKd9WUAkzlJlTQ="
        },
        "indexValueMap": {
          "fGb3sf5awPSRzMeLPrWbtH6abJ5n6v+UJ7iDO+7tp4Y=": {
            "valueMac": {
              "type": "Buffer",
              "data": "43Bu3cwzXVVXWyMcZ7FcJzIl2p+ZHA4wJj75pASsUPo="
            }
          },
          "jwbXcMKiVPKw39DBIGf1mlxoh44XgBlRA8HRNU0JeuI=": {
            "valueMac": {
              "type": "Buffer",
              "data": "UCUFTluXq4VQrsQSj3Hk3kJEJNUgT/CKvNIe0xfxygo="
            }
          },
          "VX4kGHWcQbB+dOdS2KIRhL3Y22rUhXwcmTk01OiSrCY=": {
            "valueMac": {
              "type": "Buffer",
              "data": "rtEGFFbEnPL/dIyMN7S0xQzrL9rjtfmc3mTaESjcZpA="
            }
          },
          "FCnIqhCTRx6qCS+5VuC4KgfrS/O2/TyBGIcdi1iPQjA=": {
            "valueMac": {
              "type": "Buffer",
              "data": "gFXb1I5R7RO4d1KXfddoSGYeNMfwRQfdcOXV0Si+xvc="
            }
          },
          "pyzKhg8ro5JzqVYLagCGKb4zCxnZXPLwFBIwS4TiNMQ=": {
            "valueMac": {
              "type": "Buffer",
              "data": "l75JrvCJyXRxyz1ueudTLoEDuypxBeQ0dbR49NElalM="
            }
          },
          "Uy/45dSuk8Eb/7rN/Iq5X3cZTZsJ7wXlBnz6fq+mcss=": {
            "valueMac": {
              "type": "Buffer",
              "data": "MZp/WL0rT3ETkU8d+BPRNt5z2HBGvY4aLexphgR95xA="
            }
          },
          "DyuoJdmH4sEHzdF8t6oBIBsW/WT+M79O78gXovFPCH4=": {
            "valueMac": {
              "type": "Buffer",
              "data": "ieHjNjNMe5Ja7U+XQxBYtbOZtDyVlUa3aflN/rJuwYQ="
            }
          },
          "/SAc/M6o3NcIwrt2FpoLrjx+6eHvALIrdXFcabzeS48=": {
            "valueMac": {
              "type": "Buffer",
              "data": "U8gcszsLgXKG+7ZfZqhT8vlJGYwxBqmcnWXLJGe+Xyg="
            }
          }
        }
      }
    },
    "senderKeyMemory": {
      "120363044408246178@g.us": {
        "6283803556993@s.whatsapp.net": true
      }
    }
  }
}